iris_idealai/__init__.py
iris_idealai/script.py
iris_idealai-2.5.dist-info/METADATA
iris_idealai-2.5.dist-info/WHEEL
iris_idealai-2.5.dist-info/top_level.txt
iris_idealai-2.5.dist-info/RECORD
