Metadata-Version: 2.1
Name: iris_idealai
Version: 2.5
Summary: A module to interact with Iris developed by Ideal AI
Home-page: https://idealai.netlify.app
Author: Ideal AI
Author-email: idealai@gmail.com
Classifier: Programming Language :: Python :: 3
Classifier: License :: OSI Approved :: MIT License
Classifier: Operating System :: OS Independent
Requires-Python: >=3.6
Requires-Dist: google-generativeai
Requires-Dist: pillow
Requires-Dist: requests
